ties/__init__.py
ties/convert.py
ties/exceptions.py
ties/schema_order.py
ties/schema_validation.py
ties/semantic_validation.py
ties/cli/__init__.py
ties/cli/ties_convert.py
ties/cli/ties_format.py
ties/cli/ties_validate.py
ties/cli/test/__init__.py
ties/cli/test/ties_convert_tests.py
ties/cli/test/ties_format_tests.py
ties/cli/test/ties_validate_tests.py
ties/data_binding/__init__.py
ties/data_binding/_data_binding.py
ties/schemata/__init__.py
ties/schemata/ties-base.json
ties/test/__init__.py
ties/test/__main__.py
ties/test/convert_tests.py
ties/test/data_binding_tests.py
ties/test/exceptions_tests.py
ties/test/schema_validation_tests.py
ties/test/semantic_validation_tests.py
ties/util/__init__.py
ties/util/build_number.txt
ties/util/build_time.txt
ties/util/testing.py
ties/util/version.py
ties_lib-0.9.1.dist-info/COPYING
ties_lib-0.9.1.dist-info/LICENSE
ties_lib-0.9.1.dist-info/METADATA
ties_lib-0.9.1.dist-info/NOTICE
ties_lib-0.9.1.dist-info/WHEEL
ties_lib-0.9.1.dist-info/entry_points.txt
ties_lib-0.9.1.dist-info/top_level.txt
ties_lib-0.9.1.dist-info/RECORD
