Metadata-Version: 2.1
Name: ties-lib
Version: 0.9.1
Summary: Triage Import Export Schema (TIES)
Home-page: https://github.com/Noblis/ties-lib
Author: Zack Hutzell
Author-email: zack.hutzell@noblis.org
License: Apache License, Version 2.0
Platform: UNKNOWN
Classifier: Development Status :: 4 - Beta
Classifier: Intended Audience :: Developers
Classifier: Topic :: Software Development :: Libraries
Classifier: License :: OSI Approved :: Apache Software License
Classifier: Programming Language :: Python :: 2
Classifier: Programming Language :: Python :: 2.7
Classifier: Programming Language :: Python :: 3
Classifier: Programming Language :: Python :: 3.4
Classifier: Programming Language :: Python :: 3.5
Classifier: Programming Language :: Python :: 3.6
Classifier: Programming Language :: Python :: 3.7
Requires-Python: >=2.7, !=3.0.*, !=3.1.*, !=3.2.*, !=3.3.*
Requires-Dist: attrs (~=19.1)
Requires-Dist: inflection (~=0.3)
Requires-Dist: jsonschema (~=3.0)
Requires-Dist: six (~=1.0)
Requires-Dist: typing (~=3.7)
